bme280/__init__.py
pimoroni_bme280-0.1.1.dist-info/LICENSE.txt
pimoroni_bme280-0.1.1.dist-info/METADATA
pimoroni_bme280-0.1.1.dist-info/WHEEL
pimoroni_bme280-0.1.1.dist-info/top_level.txt
pimoroni_bme280-0.1.1.dist-info/RECORD
